fastapi_testrunner/__init__.py
fastapi_testrunner/input_format.py
fastapi_testrunner/random_datas.py
fastapi_testrunner/test.py
fastapi_testrunner/test_logs.py
fastapi_testrunner-0.1.2.dist-info/licenses/LICENSE
fastapi_testrunner-0.1.2.dist-info/METADATA
fastapi_testrunner-0.1.2.dist-info/WHEEL
fastapi_testrunner-0.1.2.dist-info/top_level.txt
fastapi_testrunner-0.1.2.dist-info/RECORD
