Metadata-Version: 2.4
Name: fastapi-testrunner
Version: 0.1.2
Summary: Automated testing utility for FastAPI applications
Home-page: https://github.com/Siva-Rajan-R/fastapi_testrunner.git
Author: Siva Rajan R
Author-email: debuggers437@gmail.com
License: MIT
Keywords: fastapi testing automation openapi starlette test testrunner quciktest fastapi-testrunner test-paths
Classifier: Programming Language :: Python :: 3
Classifier: Framework :: FastAPI
Classifier: License :: OSI Approved :: MIT License
Classifier: Operating System :: OS Independent
Requires-Python: >=3.8
License-File: LICENSE
Requires-Dist: requests>=2.32.5
Requires-Dist: rich>=14.1.0
Dynamic: author
Dynamic: author-email
Dynamic: classifier
Dynamic: description
Dynamic: description-content-type
Dynamic: home-page
Dynamic: keywords
Dynamic: license
Dynamic: license-file
Dynamic: requires-dist
Dynamic: requires-python
Dynamic: summary
